tknops_llm/__init__.py
tknops_llm/client.py
tknops_llm-0.0.5.dist-info/METADATA
tknops_llm-0.0.5.dist-info/WHEEL
tknops_llm-0.0.5.dist-info/licenses/LICENSE
tknops_llm-0.0.5.dist-info/RECORD
