Metadata-Version: 2.4
Name: tknops-llm
Version: 0.0.5
Summary: Precise Token Tracking SDK for tknOps
Project-URL: Homepage, https://tknops.io
Project-URL: Documentation, https://docs.tknops.io
Author-email: tknOps <sujith@tknops.io>
License-File: LICENSE
Requires-Python: >=3.8
Requires-Dist: requests>=2.25.0
